django_ory_auth/__init__.py
django_ory_auth/apps.py
django_ory_auth/backend.py
django_ory_auth/context.py
django_ory_auth/middleware.py
django_ory_auth/models.py
django_ory_auth/tests.py
django_ory_auth/views.py
django_ory_auth-0.1.3.dist-info/LICENSE
django_ory_auth-0.1.3.dist-info/WHEEL
django_ory_auth-0.1.3.dist-info/METADATA
django_ory_auth-0.1.3.dist-info/RECORD
