Metadata-Version: 2.1
Name: django-ory-auth
Version: 0.1.3
Summary: A django package to enable integration with Ory Cloud
Home-page: https://github.com/gen1us2k/django_ory_auth
License: Apache 2
Keywords: django,ory cloud,auth
Author: Andrew Minkin
Author-email: minkin.andrew@gmail.com
Requires-Python: >=3.7,<4.0
Classifier: Environment :: Web Environment
Classifier: Framework :: Django
Classifier: Framework :: Django :: 3.0
Classifier: Framework :: Django :: 4
Classifier: Framework :: Django CMS
Classifier: License :: Other/Proprietary License
Classifier: Programming Language :: Python :: 3
Classifier: Programming Language :: Python :: 3.10
Classifier: Programming Language :: Python :: 3.7
Classifier: Programming Language :: Python :: 3.8
Classifier: Programming Language :: Python :: 3.9
Requires-Dist: Django (>3)
Requires-Dist: requests
Requires-Dist: urllib3 (>=1.26.9,<2.0.0)
Project-URL: Repository, https://github.com/gen1us2k/django_ory_auth
